finam/__init__.py
finam/config.py
finam/export.py
finam/utils.py
finam_export-2.0.0.data/scripts/download.py
finam_export-2.0.0.data/scripts/finam-download.py
finam_export-2.0.0.data/scripts/finam-lookup.py
finam_export-2.0.0.data/scripts/lookup.py
finam_export-2.0.0.dist-info/LICENSE
finam_export-2.0.0.dist-info/METADATA
finam_export-2.0.0.dist-info/WHEEL
finam_export-2.0.0.dist-info/top_level.txt
finam_export-2.0.0.dist-info/RECORD
