Metadata-Version: 2.1
Name: finam-export
Version: 2.0.0
Summary: Python library to download historical data from finam.ru
Home-page: https://github.com/ffeast/finam-export
Author: ffeast
Author-email: ffeast@gmail.com
License: Apache-2
Platform: UNKNOWN
Requires-Python: >=2.7, !=3.0.*, !=3.1.*, !=3.2.*, !=3.3.*, !=3.4.*, !=3.5.*, <4
Requires-Dist: pandas (>=0.24.2)
Requires-Dist: requests (<3,>=2.20.0)
Requires-Dist: enum34
Requires-Dist: click (>=6.7)
Requires-Dist: click-datetime (>=0.2)
